pybenproxmox/__init__.py
pybenproxmox/__main__.py
pybenproxmox/proxmox_utils.py
pybenproxmox-1.2.1.dist-info/licenses/LICENSE
pybenproxmox-1.2.1.dist-info/METADATA
pybenproxmox-1.2.1.dist-info/WHEEL
pybenproxmox-1.2.1.dist-info/top_level.txt
pybenproxmox-1.2.1.dist-info/RECORD
